tapehash/__init__.py
tapehash/algos.py
tapehash/cli.py
tapehash/work.py
tapehash-0.1.0.dist-info/METADATA
tapehash-0.1.0.dist-info/WHEEL
tapehash-0.1.0.dist-info/entry_points.txt
tapehash-0.1.0.dist-info/RECORD
