Metadata-Version: 2.4
Name: tapehash
Version: 0.1.0
Summary: Simple proof-of-work system that uses many hash algorithms.
Project-URL: Homepage, https://github.com/k98kurz/tapehash
Project-URL: Repository, https://github.com/k98kurz/tapehash
Project-URL: Bug Tracker, https://github.com/k98kurz/tapehash/issues
Author-email: k98kurz <k98kurz@gmail.com>
Classifier: Development Status :: 4 - Beta
Classifier: Intended Audience :: Developers
Classifier: License :: OSI Approved :: ISC License (ISCL)
Classifier: Operating System :: OS Independent
Classifier: Programming Language :: Python :: 3
Classifier: Topic :: Security :: Cryptography
Requires-Python: >=3.10
